README.md
setup.py
advanced_pca/__init__.py
advanced_pca/custom_pca.py
advanced_pca.egg-info/PKG-INFO
advanced_pca.egg-info/SOURCES.txt
advanced_pca.egg-info/dependency_links.txt
advanced_pca.egg-info/not-zip-safe
advanced_pca.egg-info/top_level.txt