Metadata-Version: 1.0
Name: advanced-pca
Version: 0.1
Summary: PCA with varimax rotation and feature selection
Home-page: UNKNOWN
Author: Alfred Sasko
Author-email: alfred.sasko@gmail.com
License: UNKNOWN
Platform: UNKNOWN
